pchem/__init__.py
pchem/calorimetry.py
pchem/calorimetry_old.py
pchem-0.3.1.dist-info/LICENSE
pchem-0.3.1.dist-info/METADATA
pchem-0.3.1.dist-info/WHEEL
pchem-0.3.1.dist-info/top_level.txt
pchem-0.3.1.dist-info/RECORD
