Metadata-Version: 2.1
Name: pchem
Version: 0.3.1
Summary: Physical Chemistry helper functions, scripts and tools.
Home-page: https://github.com/ryanpdwyer/pchem
Author: Ryan Dwyer
Author-email: dwyerry@mountunion.edu
License: MIT
License-File: LICENSE
Requires-Dist: sympy
